<?xml version="1.0" encoding="utf-8"?>
<cms.webpagescope>
  <WebPageScopeGUID>4511d7e9-88e5-4eed-91e1-cd2c9cf075d3</WebPageScopeGUID>
  <WebPageScopeIncludeChildren>False</WebPageScopeIncludeChildren>
  <WebPageScopeWebsiteChannelID>
    <GUID>55e3ae4b-3843-46b8-95d5-79611c371d6f</GUID>
    <ObjectType>cms.websitechannel</ObjectType>
    <Parent>
      <CodeName>DancingGoatPages</CodeName>
      <GUID>c430f96d-bd56-4448-b6ab-bce41a58f186</GUID>
      <ObjectType>cms.channel</ObjectType>
    </Parent>
  </WebPageScopeWebsiteChannelID>
</cms.webpagescope>